<?xml version="1.0" encoding="utf-8"?>

<ObjectModel>
  <Item Name="Application">
    <ChildNode TypeName="Tables"/>
    <ChildNode TypeName="Pages"/>
  </Item>
  <AbstractItem Name="Object">
    <Identifier Name="ID" TypeName="int"/>
    <Identifier Name="Name" TypeName="string"/>
    <ChildNode TypeName="ObjectProperties"/>
    <Item Name="Table">
      <ChildNode Name="Properties" TypeName="TableProperties"/>
    </Item>
    <Item Name="Page">
      <ChildNode Name="Properties" TypeName="PageProperties"/>      
    </Item>
  </AbstractItem>
  <PropertyCollection Name="ObjectProperties">
    <Property TypeName="NullableDateTimeProperty" Name="DateTime"/>
    <Property TypeName="BooleanProperty" Name="Modified"/>
    <Property TypeName="StringProperty" Name="VersionList"/>
  </PropertyCollection>
  <PropertyCollection Name="TableProperties">    
    <Property TypeName=""
  </PropertyCollection>
</ObjectModel>

